Bigquery_Email_extractor/__init__.py
Bigquery_Email_extractor/main.py
Bigquery_Email_extractor-0.0.dist-info/METADATA
Bigquery_Email_extractor-0.0.dist-info/WHEEL
Bigquery_Email_extractor-0.0.dist-info/entry_points.txt
Bigquery_Email_extractor-0.0.dist-info/top_level.txt
Bigquery_Email_extractor-0.0.dist-info/RECORD
