Metadata-Version: 2.1
Name: Bigquery-Email-extractor
Version: 0.0
Requires-Dist: google-cloud-bigquery
Requires-Dist: pandas
